sss/__init__.py
sss/core.py
sss/util.py
sss/stores/__init__.py
sss/stores/base.py
sss/stores/file.py
sss/stores/frame.py
esses-0.0.2.dist-info/LICENSE
esses-0.0.2.dist-info/METADATA
esses-0.0.2.dist-info/WHEEL
esses-0.0.2.dist-info/top_level.txt
esses-0.0.2.dist-info/RECORD
